{
  "kind": "collectionType",
  "collectionName": "relatedwords",
  "info": {
    "singularName": "relatedword",
    "pluralName": "relatedwords",
    "displayName": "relatedword",
    "description": ""
  },
  "options": {
    "draftAndPublish": true
  },
  "pluginOptions": {},
  "attributes": {
    "word": {
      "type": "string",
      "required": true,
      "default": "relatedwords"
    },
    "tags": {
      "type": "relation",
      "relation": "manyToMany",
      "target": "api::tag.tag",
      "inversedBy": "relatedwords"
    }
  }
}
